<?xml version="1.0" encoding="utf-8"?>
<ModelClass Name="MaksPowerBattLithium2x150Ah12V">
    <Description>Simulation model for MaksPower 2x12V 300Ah lithium batteries</Description>
    <ModelClassObject ParentGlobalID="MaksPower.Source">
        <DataItemsCollection>
            <DataListClasses Name="Ids::Source::DataBattery" NameObject="Data">
                <Item NameClass="DataBattery" NameObject="BatteryData" />
            </DataListClasses>
            <DataListClasses Name="Ids::Source::DataBatteryModel" NameObject="Data">
                <Item NameClass="DataBatteryModel" NameObject="ModelData" />
            </DataListClasses>
        </DataItemsCollection>
        <Sequence />
    </ModelClassObject>
</ModelClass>